iflearn.py
iflearn-1.0.0.dist-info/WHEEL
iflearn-1.0.0.dist-info/METADATA
iflearn-1.0.0.dist-info/RECORD
