Metadata-Version: 2.1
Name: iflearn
Version: 1.0.0
Summary: Test if (the lib for book)
Author: tikotstudio
Author-email: tikotstudio@yandex.ru
Requires-Python: >=3.9,<4.0
Classifier: Programming Language :: Python :: 3
Classifier: Programming Language :: Python :: 3.9
